inkamusic/__init__.py
inkamusic/__main__.py
inkamusic/algorithms.py
inkamusic/bar_distribution.py
inkamusic/basic_rhythms.py
inkamusic/basic_scales.py
inkamusic/const.py
inkamusic/create_composition.py
inkamusic/general_midi_instruments.py
inkamusic/harmonies.py
inkamusic/html_data.py
inkamusic/menu_entries.py
inkamusic/midiutil.py
inkamusic/music_parameter.py
inkamusic/rhythm_algorithms.py
inkamusic/settings.py
inkamusic/startup.py
inkamusic/structures.py
inkamusic/trackinfo_util.py
inkamusic/utilities.py
inkamusic/webutilities.py
inkamusic/public/algomusic.css
inkamusic/public/empty.gif
inkamusic/public/favicon-16x16.png
inkamusic/public/favicon-32x32.png
inkamusic/public/favicon.ico
inkamusic/public/favicon.png
inkamusic/public/inkalogo.png
inkamusic/public/spinball.gif
inkamusic/public/midi/empty.mid
inkamusic-0.2.1.dist-info/AUTHORS.rst
inkamusic-0.2.1.dist-info/LICENSE
inkamusic-0.2.1.dist-info/METADATA
inkamusic-0.2.1.dist-info/WHEEL
inkamusic-0.2.1.dist-info/entry_points.txt
inkamusic-0.2.1.dist-info/top_level.txt
inkamusic-0.2.1.dist-info/RECORD
