Metadata-Version: 2.1
Name: inkamusic
Version: 0.2.1
Summary: inkamusic creates rule based fully arranged instrumental music.
Home-page: https://github.com/physicsware/inkamusic
Author: Udo Wollschläger
Author-email: udo.wollschlaeger@gmail.com
License: GNU General Public License v3
Keywords: inkamusic
Platform: UNKNOWN
Classifier: Development Status :: 2 - Pre-Alpha
Classifier: Intended Audience :: Developers
Classifier: License :: OSI Approved :: GNU General Public License v3 (GPLv3)
Classifier: Natural Language :: English
Classifier: Programming Language :: Python :: 3
Classifier: Programming Language :: Python :: 3.5
Classifier: Programming Language :: Python :: 3.6
Classifier: Programming Language :: Python :: 3.7
Requires-Python: >=3.0, !=3.0.*, !=3.1.*, !=3.2.*, !=3.3.*, !=3.4.*
Requires-Dist: cherrypy
